Metadata-Version: 1.1
Name: desfire
Version: 0.2
Summary: MIFARE DESFire NFC card communication protocol
Home-page: https://github.com/miohtama/desfire
Author: Mikko Ohtamaa
Author-email: mikko@opensourcehacker.com
License: BSD
Keywords: desfire nfc mifare 14443
Platform: UNKNOWN
Classifier: Development Status :: 3 - Alpha
Classifier: Intended Audience :: Developers
Classifier: Natural Language :: English
Classifier: Programming Language :: Python :: 2
Classifier: Programming Language :: Python :: 2.7
Classifier: Programming Language :: Python :: 3
Classifier: Programming Language :: Python :: 3.3
Classifier: Programming Language :: Python :: 3.4
Classifier: Programming Language :: Python :: 3.5
